README.md
setup.py
pso_solver/__init__.py
pso_solver/pso_solver.py
pso_solver.egg-info/PKG-INFO
pso_solver.egg-info/SOURCES.txt
pso_solver.egg-info/dependency_links.txt
pso_solver.egg-info/requires.txt
pso_solver.egg-info/top_level.txt